pyrangeyes/__init__.py
pyrangeyes/_version.py
pyrangeyes/core.py
pyrangeyes/data_preparation.py
pyrangeyes/example_data.py
pyrangeyes/introns_off.py
pyrangeyes/make_subsets.py
pyrangeyes/names.py
pyrangeyes/plot_features.py
pyrangeyes/plot_main.py
pyrangeyes/pr_register_plot.py
pyrangeyes/data/homo_sapiens_clinically_associated.vcf
pyrangeyes/data/ncbi.gff3
pyrangeyes/data/ncbi.vcf
pyrangeyes/matplotlib_base/__init__.py
pyrangeyes/matplotlib_base/core.py
pyrangeyes/matplotlib_base/data2plot.py
pyrangeyes/matplotlib_base/fig_axes.py
pyrangeyes/matplotlib_base/plot_exons_plt.py
pyrangeyes/plotly_base/__init__.py
pyrangeyes/plotly_base/core.py
pyrangeyes/plotly_base/data2plot.py
pyrangeyes/plotly_base/fig_axes.py
pyrangeyes/plotly_base/plot_exons_ply.py
pyrangeyes/vcf/__init__.py
pyrangeyes/vcf/vcf_preparation.py
pyrangeyes/vcf/vcf_reader.py
pyrangeyes-0.1.9.dist-info/licenses/LICENSE
pyrangeyes-0.1.9.dist-info/METADATA
pyrangeyes-0.1.9.dist-info/WHEEL
pyrangeyes-0.1.9.dist-info/top_level.txt
pyrangeyes-0.1.9.dist-info/RECORD
