Metadata-Version: 2.4
Name: pyrangeyes
Version: 0.1.9
Summary: 'Genomic intervals data visualization package for dataframe objects generated with PyRanges.'
Home-page: https://github.com/pyranges/pyrangeyes
Author: Ester Muñoz del Campo, Max Ticó, Marco Mariotti
Author-email: ester.munoz01@estudiant.upf.edu, max.tico@ub.edu, marco.mariotti@ub.edu
Classifier: Programming Language :: Python :: 3
Classifier: License :: OSI Approved :: MIT License
Classifier: Operating System :: OS Independent
Requires-Python: >=3.12
License-File: LICENSE
Requires-Dist: pyranges1>=1.1.0
Requires-Dist: intervaltree>=3.1.0
Requires-Dist: deepdiff
Requires-Dist: numpy>=2.1
Requires-Dist: pandas>=2.0
Requires-Dist: ipywidgets>=8.0
Provides-Extra: matplotlib
Requires-Dist: matplotlib>=3.7.2; extra == "matplotlib"
Requires-Dist: mplcursors>=0.5.2; extra == "matplotlib"
Provides-Extra: plotly
Requires-Dist: plotly>=5.9.0; extra == "plotly"
Requires-Dist: dash>=2.14.0; extra == "plotly"
Requires-Dist: dash_bootstrap_components>=1.5.0; extra == "plotly"
Provides-Extra: docs
Requires-Dist: sphinx>=7.3.7; extra == "docs"
Requires-Dist: sphinx_rtd_theme>=2.0.0; extra == "docs"
Requires-Dist: sphinx-autoapi>=3.1.1; extra == "docs"
Requires-Dist: sphinxcontrib-napoleon>=0.7; extra == "docs"
Requires-Dist: memory-profiler>=0.61.0; extra == "docs"
Provides-Extra: all
Requires-Dist: matplotlib>=3.7.2; extra == "all"
Requires-Dist: mplcursors>=0.5.2; extra == "all"
Requires-Dist: plotly>=5.9.0; extra == "all"
Requires-Dist: dash>=2.14.0; extra == "all"
Requires-Dist: dash_bootstrap_components>=1.5.0; extra == "all"
Requires-Dist: sphinx>=7.3.7; extra == "all"
Requires-Dist: sphinx_rtd_theme>=2.0.0; extra == "all"
Requires-Dist: sphinx-autoapi>=3.1.1; extra == "all"
Requires-Dist: sphinxcontrib-napoleon>=0.7; extra == "all"
Requires-Dist: memory-profiler>=0.61.0; extra == "all"
Requires-Dist: ipywidgets>=8.0; extra == "all"
Dynamic: license-file
